<annotation>
	<folder>11-recyclables-paper bags</folder>
	<filename>img_3399.jpg</filename>
	<path>E:\example\PycharmProjects\datasets\ljok\ljok\new_img\img_3399.jpg</path>
	<source>
		<database>Unknown</database>
	</source>
	<size>
		<width>300</width>
		<height>400</height>
		<depth>3</depth>
	</size>
	<segmented>0</segmented>
	<object>
		<name>11/可回收垃圾/纸袋</name>
		<pose>Unspecified</pose>
		<truncated>0</truncated>
		<difficult>0</difficult>
		<bndbox>
			<xmin>5</xmin>
			<ymin>23</ymin>
			<xmax>282</xmax>
			<ymax>185</ymax>
		</bndbox>
	</object>
	<object>
		<name>11/可回收垃圾/纸袋</name>
		<pose>Unspecified</pose>
		<truncated>1</truncated>
		<difficult>0</difficult>
		<bndbox>
			<xmin>1</xmin>
			<ymin>64</ymin>
			<xmax>262</xmax>
			<ymax>216</ymax>
		</bndbox>
	</object>
</annotation>