<annotation>
	<folder>9-recyclables-rope</folder>
	<filename>img_1186.jpg</filename>
	<path>E:\example\PycharmProjects\datasets\ljok\ljok\new_img\img_1186.jpg</path>
	<source>
		<database>Unknown</database>
	</source>
	<size>
		<width>236</width>
		<height>295</height>
		<depth>3</depth>
	</size>
	<segmented>0</segmented>
	<object>
		<name>9/可回收垃圾/绳子</name>
		<pose>Unspecified</pose>
		<truncated>1</truncated>
		<difficult>0</difficult>
		<bndbox>
			<xmin>1</xmin>
			<ymin>18</ymin>
			<xmax>107</xmax>
			<ymax>56</ymax>
		</bndbox>
	</object>
	<object>
		<name>9/可回收垃圾/绳子</name>
		<pose>Unspecified</pose>
		<truncated>0</truncated>
		<difficult>0</difficult>
		<bndbox>
			<xmin>122</xmin>
			<ymin>24</ymin>
			<xmax>218</xmax>
			<ymax>48</ymax>
		</bndbox>
	</object>
	<object>
		<name>9/可回收垃圾/绳子</name>
		<pose>Unspecified</pose>
		<truncated>1</truncated>
		<difficult>0</difficult>
		<bndbox>
			<xmin>1</xmin>
			<ymin>91</ymin>
			<xmax>108</xmax>
			<ymax>137</ymax>
		</bndbox>
	</object>
	<object>
		<name>9/可回收垃圾/绳子</name>
		<pose>Unspecified</pose>
		<truncated>0</truncated>
		<difficult>0</difficult>
		<bndbox>
			<xmin>138</xmin>
			<ymin>89</ymin>
			<xmax>213</xmax>
			<ymax>147</ymax>
		</bndbox>
	</object>
	<object>
		<name>9/可回收垃圾/绳子</name>
		<pose>Unspecified</pose>
		<truncated>1</truncated>
		<difficult>0</difficult>
		<bndbox>
			<xmin>1</xmin>
			<ymin>167</ymin>
			<xmax>114</xmax>
			<ymax>216</ymax>
		</bndbox>
	</object>
	<object>
		<name>9/可回收垃圾/绳子</name>
		<pose>Unspecified</pose>
		<truncated>1</truncated>
		<difficult>0</difficult>
		<bndbox>
			<xmin>1</xmin>
			<ymin>247</ymin>
			<xmax>105</xmax>
			<ymax>282</ymax>
		</bndbox>
	</object>
	<object>
		<name>9/可回收垃圾/绳子</name>
		<pose>Unspecified</pose>
		<truncated>0</truncated>
		<difficult>0</difficult>
		<bndbox>
			<xmin>122</xmin>
			<ymin>167</ymin>
			<xmax>233</xmax>
			<ymax>208</ymax>
		</bndbox>
	</object>
	<object>
		<name>9/可回收垃圾/绳子</name>
		<pose>Unspecified</pose>
		<truncated>0</truncated>
		<difficult>0</difficult>
		<bndbox>
			<xmin>123</xmin>
			<ymin>245</ymin>
			<xmax>217</xmax>
			<ymax>273</ymax>
		</bndbox>
	</object>
</annotation>