<annotation>
	<folder>6-recyclables-can</folder>
	<filename>img_1399.jpg</filename>
	<path>E:\example\PycharmProjects\datasets\ljok\ljok\new_img\img_1399.jpg</path>
	<source>
		<database>Unknown</database>
	</source>
	<size>
		<width>282</width>
		<height>282</height>
		<depth>3</depth>
	</size>
	<segmented>0</segmented>
	<object>
		<name>6/可回收垃圾/易拉罐</name>
		<pose>Unspecified</pose>
		<truncated>0</truncated>
		<difficult>0</difficult>
		<bndbox>
			<xmin>11</xmin>
			<ymin>56</ymin>
			<xmax>256</xmax>
			<ymax>245</ymax>
		</bndbox>
	</object>
</annotation>